{
  "okazejo": "Esperanto",
  "esperantujo": "Esperantujo",
  "lingvo": "Lingvo",
  "hejmo": "Hejmo",
  "pri": "Pri",
  "kial": "Kial",
  "lerni": "Lerni",

  "//": "Cxefpagxoj",

  "KioEstasEsperanto": "Kio Estas Esperanto?",
  "KioEstasEsperanto_": "Esperanto estas la plej bona lingvo.",

  "KielGxiLaboras": "Kiel Gxi Laboras?",
  "KielGxiLaboras_": "Gxi ne laboras.",

  "KialEsperanto": "Kial Lerni Esperanton?",
  "Citajxo": "La interna ideo de Esperanto estas: sur neŭtrala lingva fundamento forigi la murojn inter la gentoj kaj alkutimigadi la homojn, ke ĉiu el ili vidu en sia proksimulo nur homon kaj fraton.",

  "//": "Tradukoj",

  "saluton": "Saluton!",
  "adiaux": "Adiaŭ",
  "kielViFartas": "Kiel vi fartas?",
  "miaNomoEstas": "Mia nomo estas...",
  "salutonAlCxiuj": "Saluton al ĉiuj"
}
